bbhelper/__init__.py
bbhelper/bbhelper.py
bbhelper-0.0.1.dist-info/LICENSE
bbhelper-0.0.1.dist-info/METADATA
bbhelper-0.0.1.dist-info/WHEEL
bbhelper-0.0.1.dist-info/top_level.txt
bbhelper-0.0.1.dist-info/RECORD
