Metadata-Version: 2.1
Name: bbhelper
Version: 0.0.1
Summary: Wrapper for Bitbucket Cloud API
Author-email: Jim Vrckovski <jim.vrckovski@gmail.com>
License: MIT License        
Project-URL: Homepage, https://github.com/jvrck/bb-helper
Project-URL: Bug Tracker, https://github.com/jvrck/bb-helper/issues
Classifier: Programming Language :: Python :: 3
Classifier: License :: OSI Approved :: MIT License
Classifier: Operating System :: OS Independent
Requires-Python: >=3.7
License-File: LICENSE
Requires-Dist: requests (>=2.28.1)
